webmonitor
