Metadata-Version: 1.0
Name: webmonitor
Version: 0.3
Summary: Monitors a website by retrieving it periodically, complains if its down.
Home-page: http://github.com/mbr/webmonitor
Author: Marc Brinkmann
Author-email: git@marcbrinkmann.de
License: MIT
Platform: UNKNOWN
